agentdash/__init__.py
agentdash/annotator.py
agentdash/taxonomy.py
agentdash-0.1.0.dist-info/licenses/LICENSE
agentdash-0.1.0.dist-info/METADATA
agentdash-0.1.0.dist-info/WHEEL
agentdash-0.1.0.dist-info/top_level.txt
agentdash-0.1.0.dist-info/RECORD
