Metadata-Version: 2.4
Name: agentdash
Version: 0.1.0
Summary: Multi-Agent Systems Failure Taxonomy (MAST) annotation library using LLM-as-a-Judge
Home-page: https://github.com/multi-agent-systems-failure-taxonomy/MAST
Author: MAST Research Team
Author-email: MAST Research Team <cemri@berkeley.edu>
License: MIT License
Project-URL: Homepage, https://github.com/multi-agent-systems-failure-taxonomy/MAST
Project-URL: Bug Reports, https://github.com/multi-agent-systems-failure-taxonomy/MAST/issues
Project-URL: Source, https://github.com/multi-agent-systems-failure-taxonomy/MAST
Project-URL: Documentation, https://github.com/multi-agent-systems-failure-taxonomy/MAST
Keywords: multi-agent systems,failure taxonomy,llm judge,ai evaluation,mast
Classifier: Development Status :: 4 - Beta
Classifier: Intended Audience :: Developers
Classifier: Intended Audience :: Science/Research
Classifier: License :: OSI Approved :: MIT License
Classifier: Operating System :: OS Independent
Classifier: Programming Language :: Python :: 3
Classifier: Programming Language :: Python :: 3.8
Classifier: Programming Language :: Python :: 3.9
Classifier: Programming Language :: Python :: 3.10
Classifier: Programming Language :: Python :: 3.11
Classifier: Programming Language :: Python :: 3.12
Classifier: Topic :: Scientific/Engineering :: Artificial Intelligence
Classifier: Topic :: Software Development :: Libraries :: Python Modules
Requires-Python: >=3.8
License-File: LICENSE
Requires-Dist: openai>=1.0.0
Provides-Extra: dev
Requires-Dist: pytest>=7.0.0; extra == "dev"
Requires-Dist: pytest-cov>=4.0.0; extra == "dev"
Requires-Dist: black>=22.0.0; extra == "dev"
Requires-Dist: isort>=5.0.0; extra == "dev"
Requires-Dist: flake8>=5.0.0; extra == "dev"
Dynamic: author
Dynamic: home-page
Dynamic: license-file
Dynamic: requires-python
